PECF/__init__.py
PECF/main.py
PECF-1.0.26.dist-info/METADATA
PECF-1.0.26.dist-info/WHEEL
PECF-1.0.26.dist-info/top_level.txt
PECF-1.0.26.dist-info/RECORD
