Metadata-Version: 2.1
Name: PECF
Version: 1.0.26
Summary: New easy and accessible configuration language
Home-page: https://github.com/Zedikon/PECF
Author: Zedikon
Author-email: mrzedikon@gmail.com
License: UNKNOWN
Platform: UNKNOWN
Classifier: Programming Language :: Python :: 3.10
Classifier: License :: OSI Approved :: GNU General Public License v3 (GPLv3)
